opencc/__init__.py
opencc/version.py
opencc/clib/include/opencc/BinaryDict.hpp
opencc/clib/include/opencc/Common.hpp
opencc/clib/include/opencc/Config.hpp
opencc/clib/include/opencc/Conversion.hpp
opencc/clib/include/opencc/ConversionChain.hpp
opencc/clib/include/opencc/Converter.hpp
opencc/clib/include/opencc/DartsDict.hpp
opencc/clib/include/opencc/Dict.hpp
opencc/clib/include/opencc/DictConverter.hpp
opencc/clib/include/opencc/DictEntry.hpp
opencc/clib/include/opencc/DictGroup.hpp
opencc/clib/include/opencc/Exception.hpp
opencc/clib/include/opencc/Export.hpp
opencc/clib/include/opencc/Lexicon.hpp
opencc/clib/include/opencc/MarisaDict.hpp
opencc/clib/include/opencc/MaxMatchSegmentation.hpp
opencc/clib/include/opencc/Optional.hpp
opencc/clib/include/opencc/PhraseExtract.hpp
opencc/clib/include/opencc/Segmentation.hpp
opencc/clib/include/opencc/Segments.hpp
opencc/clib/include/opencc/SerializableDict.hpp
opencc/clib/include/opencc/SerializedValues.hpp
opencc/clib/include/opencc/SimpleConverter.hpp
opencc/clib/include/opencc/TextDict.hpp
opencc/clib/include/opencc/UTF8StringSlice.hpp
opencc/clib/include/opencc/UTF8Util.hpp
opencc/clib/include/opencc/opencc.h
opencc/clib/lib/libopencc.1.0.0.dylib
opencc/clib/lib/libopencc.2.dylib
opencc/clib/lib/libopencc.dylib
opencc/clib/share/opencc/HKVariants.ocd2
opencc/clib/share/opencc/HKVariantsRev.ocd2
opencc/clib/share/opencc/HKVariantsRevPhrases.ocd2
opencc/clib/share/opencc/JPShinjitaiCharacters.ocd2
opencc/clib/share/opencc/JPShinjitaiPhrases.ocd2
opencc/clib/share/opencc/JPVariants.ocd2
opencc/clib/share/opencc/JPVariantsRev.ocd2
opencc/clib/share/opencc/STCharacters.ocd2
opencc/clib/share/opencc/STPhrases.ocd2
opencc/clib/share/opencc/TSCharacters.ocd2
opencc/clib/share/opencc/TSPhrases.ocd2
opencc/clib/share/opencc/TWPhrases.ocd2
opencc/clib/share/opencc/TWPhrasesRev.ocd2
opencc/clib/share/opencc/TWVariants.ocd2
opencc/clib/share/opencc/TWVariantsRev.ocd2
opencc/clib/share/opencc/TWVariantsRevPhrases.ocd2
opencc_py-1.1.0.dist-info/METADATA
opencc_py-1.1.0.dist-info/WHEEL
opencc_py-1.1.0.dist-info/top_level.txt
opencc_py-1.1.0.dist-info/RECORD
